memstore/__init__.py
memstore/_memstore.py
memstore-0.2.5.3.dist-info/LICENSE
memstore-0.2.5.3.dist-info/METADATA
memstore-0.2.5.3.dist-info/WHEEL
memstore-0.2.5.3.dist-info/RECORD
