Metadata-Version: 2.3
Name: memstore
Version: 0.2.5.3
Summary: 
Author: Chang Cheng
Author-email: changcheng@bwbtech.net
Requires-Python: >=3.10
Classifier: Programming Language :: Python :: 3
Classifier: Programming Language :: Python :: 3.10
Classifier: Programming Language :: Python :: 3.11
Classifier: Programming Language :: Python :: 3.12
Classifier: Programming Language :: Python :: 3.13
